tidb_vector/__init__.py
tidb_vector/integrations/__init__.py
tidb_vector/integrations/vector_client.py
tidb_vector/sqlalchemy/__init__.py
tidbvec-0.0.6.dist-info/LICENSE
tidbvec-0.0.6.dist-info/METADATA
tidbvec-0.0.6.dist-info/WHEEL
tidbvec-0.0.6.dist-info/RECORD
